nautobot_cable_utils/__init__.py
nautobot_cable_utils/admin.py
nautobot_cable_utils/api/__init__.py
nautobot_cable_utils/api/filters.py
nautobot_cable_utils/api/serializers.py
nautobot_cable_utils/api/urls.py
nautobot_cable_utils/api/views.py
nautobot_cable_utils/cable_router.py
nautobot_cable_utils/filters.py
nautobot_cable_utils/forms.py
nautobot_cable_utils/migrations/0001_initial.py
nautobot_cable_utils/migrations/0002_auto_20220808_0747.py
nautobot_cable_utils/migrations/0003_rename_tenant_cabletemplate_owner.py
nautobot_cable_utils/migrations/0004_rename_cable_number_cabletemplate_name.py
nautobot_cable_utils/migrations/0005_alter_cabletemplate_name.py
nautobot_cable_utils/migrations/0006_auto_20230117_1657.py
nautobot_cable_utils/migrations/0007_alter_cabletemplate_supplier.py
nautobot_cable_utils/migrations/0008_auto_20230324_1055.py
nautobot_cable_utils/migrations/0009_auto_20230802_0724.py
nautobot_cable_utils/migrations/0010_rename_cabletemplate_cableinventoryitem.py
nautobot_cable_utils/migrations/0011_auto_20240621_1409.py
nautobot_cable_utils/migrations/__init__.py
nautobot_cable_utils/models.py
nautobot_cable_utils/navigation.py
nautobot_cable_utils/static/nautobot_cable_utils/html5-qrcode.min.js
nautobot_cable_utils/static/nautobot_cable_utils/qr-scanner.js
nautobot_cable_utils/tables.py
nautobot_cable_utils/template_content.py
nautobot_cable_utils/templates/nautobot_cable_utils/bulk_commission.html
nautobot_cable_utils/templates/nautobot_cable_utils/cable_connect.html
nautobot_cable_utils/templates/nautobot_cable_utils/cable_router_add.html
nautobot_cable_utils/templates/nautobot_cable_utils/cable_router_verify.html
nautobot_cable_utils/templates/nautobot_cable_utils/cable_utils_base.html
nautobot_cable_utils/templates/nautobot_cable_utils/cableinventoryitem.html
nautobot_cable_utils/templates/nautobot_cable_utils/cableinventoryitem_bulk_add.html
nautobot_cable_utils/templates/nautobot_cable_utils/cableinventoryitem_edit.html
nautobot_cable_utils-1.0.4.dist-info/LICENSE.txt
nautobot_cable_utils-1.0.4.dist-info/METADATA
nautobot_cable_utils-1.0.4.dist-info/WHEEL
nautobot_cable_utils-1.0.4.dist-info/RECORD
