Metadata-Version: 2.3
Name: nautobot-cable-utils
Version: 1.0.4
Summary: A Nautobot plugin for working with cables
License: Apache-2.0
Author: Gesellschaft für wissenschaftliche Datenverarbeitung mbH Göttingen
Requires-Python: >=3.11,<3.12
Classifier: License :: OSI Approved :: Apache Software License
Classifier: Programming Language :: Python :: 3
Classifier: Programming Language :: Python :: 3.11
Requires-Dist: igraph (>=0.11.5,<0.12.0)
Requires-Dist: nautobot (>=2.0.0,<3.0.0)
Project-URL: Repository, https://gitlab-ce.gwdg.de/gwdg-netz/nautobot-plugins/nautobot-cable-utils
